dpt_threading/__init__.py
dpt_threading/event.py
dpt_threading/instance_lock.py
dpt_threading/result_event.py
dpt_threading/thread_lock.py
dpt_threading/encapsulated/__init__.py
dpt_threading/encapsulated/thread.py
dpt_threading-2.0.2.data/data/docs/LICENSE
dpt_threading-2.0.2.data/data/docs/README
dpt_threading-2.0.2.dist-info/LICENSE
dpt_threading-2.0.2.dist-info/METADATA
dpt_threading-2.0.2.dist-info/WHEEL
dpt_threading-2.0.2.dist-info/top_level.txt
dpt_threading-2.0.2.dist-info/RECORD
